yaspeller.py
YandexSpeller-1.0.0.dist-info/METADATA
YandexSpeller-1.0.0.dist-info/WHEEL
YandexSpeller-1.0.0.dist-info/top_level.txt
YandexSpeller-1.0.0.dist-info/RECORD
